setup.py
tests/__init__.py
tests/dealer_test.py
tests/main_test.py
tests/runner_test.py
tests/sender_test.py
tsuru_router_tailer/__init__.py
tsuru_router_tailer/dealer.py
tsuru_router_tailer/main.py
tsuru_router_tailer/runner.py
tsuru_router_tailer/sender.py
tsuru_router_tailer.egg-info/PKG-INFO
tsuru_router_tailer.egg-info/SOURCES.txt
tsuru_router_tailer.egg-info/dependency_links.txt
tsuru_router_tailer.egg-info/entry_points.txt
tsuru_router_tailer.egg-info/requires.txt
tsuru_router_tailer.egg-info/top_level.txt