Metadata-Version: 1.1
Name: tsuru-router-tailer
Version: 0.3
Summary: Send tsuru router log and send to logstash
Home-page: https://github.com/guilhermef/tsuru-router-tailer
Author: Guilherme Souza
Author-email: guivideojob@gmail.com
License: MIT
Keywords: tsuru router log logstash
Platform: UNKNOWN
Classifier: Development Status :: 4 - Beta
Classifier: Intended Audience :: Developers
Classifier: License :: OSI Approved :: MIT License
Classifier: Natural Language :: English
Classifier: Operating System :: MacOS
Classifier: Operating System :: POSIX :: Linux
Classifier: Programming Language :: Python :: 3.5
